Metadata-Version: 1.0
Name: OM-distributions
Version: 0.1
Summary: Gaussian distributions
Home-page: UNKNOWN
Author: Udacity
Author-email: UNKNOWN
License: UNKNOWN
Platform: UNKNOWN
